indoorContact/__init__.py
indoorContact/indoorContact.py
indoorContact/sampleData/exp_space2.xlsx
indoorContact/sampleData/exp_space3.xlsx
indoorContact/sampleData/obstacle_space.xlsx
indoorContact-0.1.0.dist-info/METADATA
indoorContact-0.1.0.dist-info/WHEEL
indoorContact-0.1.0.dist-info/top_level.txt
indoorContact-0.1.0.dist-info/RECORD
