Metadata-Version: 2.1
Name: indoorContact
Version: 0.1.0
Summary: ABM pedestrian simulation counting indoor contact
Home-page: https://github.com/MG-Choi/indoorCont.git
Author: MoongiChoi
Author-email: u1316663@utah.edu
License: UNKNOWN
Platform: UNKNOWN
Requires-Dist: matplotlib
Requires-Dist: pandas
Requires-Dist: numpy
Requires-Dist: tqdm
Requires-Dist: celluloid (>=0.2.0)
Requires-Dist: seaborn (>=0.12.2)
